{"categoryStats":["FGM","FG%","FT%","3PTM","PTS","REB","AST","ST","BLK","TO"],"nonCategoryStats":["GM","GP","GS","MIN","FGA","FTM","FTA","3PTA","3PT%","OREB","DREB"],"teams":{"112.l.1889.t.1":{"name":"playoffs or bust!","userName":"Andrew"},"112.l.1889.t.2":{"name":"I.L. Whore","userName":"Calvin"},"112.l.1889.t.3":{"name":"colin's bitch","userName":"Anthony"},"112.l.1889.t.4":{"name":"Wutown Wusters","userName":"Felix"},"112.l.1889.t.5":{"name":"team d","userName":"Darren"},"112.l.1889.t.6":{"name":"Ridirkculous!!!","userName":"Colin"},"112.l.1889.t.7":{"name":"can I win?","userName":"Victor"},"112.l.1889.t.8":{"name":"Dummy Team","userName":"Dummy"}},"matchups":{"championship":[],"consolation":[],"regular":[{"headers":[],"rows":[["112.l.1889.t.1",32.0,32.0,185.0,0.45232273838630804,0.8202247191011236,34.0,550.0,178.0,88.0,38.0,25.0,76.0,7.0],["112.l.1889.t.3",35.0,31.0,153.0,0.4434782608695652,0.6797385620915033,15.0,425.0,216.0,67.0,22.0,31.0,60.0,3.0]]},{"headers":[],"rows":[["112.l.1889.t.2",35.0,33.0,219.0,0.43887775551102204,0.7748917748917749,36.0,653.0,250.0,106.0,33.0,19.0,73.0,9.0],["112.l.1889.t.8",0.0,null,0.0,null,null,0.0,0.0,0.0,0.0,0.0,0.0,0.0,1.0]]},{"headers":[],"rows":[["112.l.1889.t.4",38.0,31.0,224.0,0.47558386411889597,0.7784810126582279,23.0,594.0,213.0,126.0,37.0,43.0,79.0,4.0],["112.l.1889.t.7",34.0,33.0,223.0,0.49776785714285715,0.6990291262135923,34.0,624.0,225.0,139.0,45.0,33.0,92.0,6.0]]},{"headers":[],"rows":[["112.l.1889.t.5",35.0,35.0,213.0,0.43380855397148677,0.6744186046511628,22.0,593.0,264.0,166.0,46.0,25.0,118.0,2.0],["112.l.1889.t.6",36.0,36.0,235.0,0.4425612052730697,0.7989949748743719,39.0,668.0,255.0,106.0,48.0,32.0,78.0,8.0]]}]},"totals":{"teamStats":{"headers":[],"rows":[["112.l.1889.t.1",32.0,32.0,23.0,1084.0,185.0,409.0,0.45232273838630804,146.0,178.0,0.8202247191011236,34.0,78.0,0.4358974358974359,550.0,43.0,135.0,178.0,88.0,38.0,25.0,76.0],["112.l.1889.t.2",35.0,33.0,33.0,1183.0,219.0,499.0,0.43887775551102204,179.0,231.0,0.7748917748917749,36.0,97.0,0.3711340206185567,653.0,53.0,197.0,250.0,106.0,33.0,19.0,73.0],["112.l.1889.t.3",35.0,31.0,29.0,943.0,153.0,345.0,0.4434782608695652,104.0,153.0,0.6797385620915033,15.0,48.0,0.3125,425.0,59.0,157.0,216.0,67.0,22.0,31.0,60.0],["112.l.1889.t.4",38.0,31.0,30.0,1136.0,224.0,471.0,0.47558386411889597,123.0,158.0,0.7784810126582279,23.0,62.0,0.3709677419354839,594.0,62.0,151.0,213.0,126.0,37.0,43.0,79.0],["112.l.1889.t.5",35.0,35.0,35.0,1272.0,213.0,491.0,0.43380855397148677,145.0,215.0,0.6744186046511628,22.0,74.0,0.2972972972972973,593.0,70.0,194.0,264.0,166.0,46.0,25.0,118.0],["112.l.1889.t.6",36.0,36.0,36.0,1309.0,235.0,531.0,0.4425612052730697,159.0,199.0,0.7989949748743719,39.0,107.0,0.3644859813084112,668.0,61.0,194.0,255.0,106.0,48.0,32.0,78.0],["112.l.1889.t.7",34.0,33.0,33.0,1191.0,223.0,448.0,0.49776785714285715,144.0,206.0,0.6990291262135923,34.0,72.0,0.4722222222222222,624.0,50.0,175.0,225.0,139.0,45.0,33.0,92.0],["112.l.1889.t.8",0.0,null,null,null,0.0,0.0,null,0.0,0.0,null,0.0,null,null,0.0,null,null,0.0,0.0,0.0,0.0,0.0]]},"roto":{"headers":[],"rows":[["112.l.1889.t.6",8.0,4.0,7.0,8.0,8.0,7.0,4.5,8.0,6.0,4.0,64.5],["112.l.1889.t.7",6.0,8.0,4.0,5.5,6.0,5.0,7.0,6.0,7.0,2.0,56.5],["112.l.1889.t.4",7.0,7.0,6.0,4.0,5.0,3.0,6.0,4.0,8.0,3.0,53.0],["112.l.1889.t.2",5.0,3.0,5.0,7.0,7.0,6.0,4.5,3.0,2.0,6.0,48.5],["112.l.1889.t.1",3.0,6.0,8.0,5.5,3.0,2.0,3.0,5.0,3.5,5.0,44.0],["112.l.1889.t.5",4.0,2.0,2.0,3.0,4.0,8.0,8.0,7.0,3.5,1.0,42.5],["112.l.1889.t.3",2.0,5.0,3.0,2.0,2.0,4.0,2.0,2.0,5.0,7.0,34.0],["112.l.1889.t.8",1.0,1.0,1.0,1.0,1.0,1.0,1.0,1.0,1.0,8.0,17.0]]},"breakdown":{"rows":[{"teamKey":"112.l.1889.t.1","cells":{"112.l.1889.t.1":{"win":0,"loss":0,"tie":0,"tooltip":null},"112.l.1889.t.2":{"win":4,"loss":6,"tie":0,"tooltip":"W: FG%, FT%, ST, BLK\nL: FGM, 3PTM, PTS, REB, AST, TO\nT: "},"112.l.1889.t.3":{"win":7,"loss":3,"tie":0,"tooltip":"W: FGM, FG%, FT%, 3PTM, PTS, AST, ST\nL: REB, BLK, TO\nT: "},"112.l.1889.t.4":{"win":4,"loss":6,"tie":0,"tooltip":"W: FT%, 3PTM, ST, TO\nL: FGM, FG%, PTS, REB, AST, BLK\nT: "},"112.l.1889.t.5":{"win":4,"loss":5,"tie":1,"tooltip":"W: FG%, FT%, 3PTM, TO\nL: FGM, PTS, REB, AST, ST\nT: BLK"},"112.l.1889.t.6":{"win":3,"loss":7,"tie":0,"tooltip":"W: FG%, FT%, TO\nL: FGM, 3PTM, PTS, REB, AST, ST, BLK\nT: "},"112.l.1889.t.7":{"win":2,"loss":7,"tie":1,"tooltip":"W: FT%, TO\nL: FGM, FG%, PTS, REB, AST, ST, BLK\nT: 3PTM"},"112.l.1889.t.8":{"win":9,"loss":1,"tie":0,"tooltip":"W: FGM, FG%, FT%, 3PTM, PTS, REB, AST, ST, BLK\nL: TO\nT: "},"total":{"win":33,"loss":35,"tie":2,"tooltip":"FGM: 2-5-0\nFG%: 5-2-0\nFT%: 7-0-0\n3PTM: 4-2-1\nPTS: 2-5-0\nREB: 1-6-0\nAST: 2-5-0\nST: 4-3-0\nBLK: 2-4-1\nTO: 4-3-0"}}},{"teamKey":"112.l.1889.t.2","cells":{"112.l.1889.t.1":{"win":6,"loss":4,"tie":0,"tooltip":"W: FGM, 3PTM, PTS, REB, AST, TO\nL: FG%, FT%, ST, BLK\nT: "},"112.l.1889.t.2":{"win":0,"loss":0,"tie":0,"tooltip":null},"112.l.1889.t.3":{"win":7,"loss":3,"tie":0,"tooltip":"W: FGM, FT%, 3PTM, PTS, REB, AST, ST\nL: FG%, BLK, TO\nT: "},"112.l.1889.t.4":{"win":4,"loss":6,"tie":0,"tooltip":"W: 3PTM, PTS, REB, TO\nL: FGM, FG%, FT%, AST, ST, BLK\nT: "},"112.l.1889.t.5":{"win":6,"loss":4,"tie":0,"tooltip":"W: FGM, FG%, FT%, 3PTM, PTS, TO\nL: REB, AST, ST, BLK\nT: "},"112.l.1889.t.6":{"win":1,"loss":8,"tie":1,"tooltip":"W: TO\nL: FGM, FG%, FT%, 3PTM, PTS, REB, ST, BLK\nT: AST"},"112.l.1889.t.7":{"win":5,"loss":5,"tie":0,"tooltip":"W: FT%, 3PTM, PTS, REB, TO\nL: FGM, FG%, AST, ST, BLK\nT: "},"112.l.1889.t.8":{"win":9,"loss":1,"tie":0,"tooltip":"W: FGM, FG%, FT%, 3PTM, PTS, REB, AST, ST, BLK\nL: TO\nT: "},"total":{"win":38,"loss":31,"tie":1,"tooltip":"FGM: 4-3-0\nFG%: 2-5-0\nFT%: 4-3-0\n3PTM: 6-1-0\nPTS: 6-1-0\nREB: 5-2-0\nAST: 3-3-1\nST: 2-5-0\nBLK: 1-6-0\nTO: 5-2-0"}}},{"teamKey":"112.l.1889.t.3","cells":{"112.l.1889.t.1":{"win":3,"loss":7,"tie":0,"tooltip":"W: REB, BLK, TO\nL: FGM, FG%, FT%, 3PTM, PTS, AST, ST\nT: "},"112.l.1889.t.2":{"win":3,"loss":7,"tie":0,"tooltip":"W: FG%, BLK, TO\nL: FGM, FT%, 3PTM, PTS, REB, AST, ST\nT: "},"112.l.1889.t.3":{"win":0,"loss":0,"tie":0,"tooltip":null},"112.l.1889.t.4":{"win":2,"loss":8,"tie":0,"tooltip":"W: REB, TO\nL: FGM, FG%, FT%, 3PTM, PTS, AST, ST, BLK\nT: "},"112.l.1889.t.5":{"win":4,"loss":6,"tie":0,"tooltip":"W: FG%, FT%, BLK, TO\nL: FGM, 3PTM, PTS, REB, AST, ST\nT: "},"112.l.1889.t.6":{"win":2,"loss":8,"tie":0,"tooltip":"W: FG%, TO\nL: FGM, FT%, 3PTM, PTS, REB, AST, ST, BLK\nT: "},"112.l.1889.t.7":{"win":1,"loss":9,"tie":0,"tooltip":"W: TO\nL: FGM, FG%, FT%, 3PTM, PTS, REB, AST, ST, BLK\nT: "},"112.l.1889.t.8":{"win":9,"loss":1,"tie":0,"tooltip":"W: FGM, FG%, FT%, 3PTM, PTS, REB, AST, ST, BLK\nL: TO\nT: "},"total":{"win":24,"loss":46,"tie":0,"tooltip":"FGM: 1-6-0\nFG%: 4-3-0\nFT%: 2-5-0\n3PTM: 1-6-0\nPTS: 1-6-0\nREB: 3-4-0\nAST: 1-6-0\nST: 1-6-0\nBLK: 4-3-0\nTO: 6-1-0"}}},{"teamKey":"112.l.1889.t.4","cells":{"112.l.1889.t.1":{"win":6,"loss":4,"tie":0,"tooltip":"W: FGM, FG%, PTS, REB, AST, BLK\nL: FT%, 3PTM, ST, TO\nT: "},"112.l.1889.t.2":{"win":6,"loss":4,"tie":0,"tooltip":"W: FGM, FG%, FT%, AST, ST, BLK\nL: 3PTM, PTS, REB, TO\nT: "},"112.l.1889.t.3":{"win":8,"loss":2,"tie":0,"tooltip":"W: FGM, FG%, FT%, 3PTM, PTS, AST, ST, BLK\nL: REB, TO\nT: "},"112.l.1889.t.4":{"win":0,"loss":0,"tie":0,"tooltip":null},"112.l.1889.t.5":{"win":7,"loss":3,"tie":0,"tooltip":"W: FGM, FG%, FT%, 3PTM, PTS, BLK, TO\nL: REB, AST, ST\nT: "},"112.l.1889.t.6":{"win":3,"loss":7,"tie":0,"tooltip":"W: FG%, AST, BLK\nL: FGM, FT%, 3PTM, PTS, REB, ST, TO\nT: "},"112.l.1889.t.7":{"win":4,"loss":6,"tie":0,"tooltip":"W: FGM, FT%, BLK, TO\nL: FG%, 3PTM, PTS, REB, AST, ST\nT: "},"112.l.1889.t.8":{"win":9,"loss":1,"tie":0,"tooltip":"W: FGM, FG%, FT%, 3PTM, PTS, REB, AST, ST, BLK\nL: TO\nT: "},"total":{"win":43,"loss":27,"tie":0,"tooltip":"FGM: 6-1-0\nFG%: 6-1-0\nFT%: 5-2-0\n3PTM: 3-4-0\nPTS: 4-3-0\nREB: 2-5-0\nAST: 5-2-0\nST: 3-4-0\nBLK: 7-0-0\nTO: 2-5-0"}}},{"teamKey":"112.l.1889.t.5","cells":{"112.l.1889.t.1":{"win":5,"loss":4,"tie":1,"tooltip":"W: FGM, PTS, REB, AST, ST\nL: FG%, FT%, 3PTM, TO\nT: BLK"},"112.l.1889.t.2":{"win":4,"loss":6,"tie":0,"tooltip":"W: REB, AST, ST, BLK\nL: FGM, FG%, FT%, 3PTM, PTS, TO\nT: "},"112.l.1889.t.3":{"win":6,"loss":4,"tie":0,"tooltip":"W: FGM, 3PTM, PTS, REB, AST, ST\nL: FG%, FT%, BLK, TO\nT: "},"112.l.1889.t.4":{"win":3,"loss":7,"tie":0,"tooltip":"W: REB, AST, ST\nL: FGM, FG%, FT%, 3PTM, PTS, BLK, TO\nT: "},"112.l.1889.t.5":{"win":0,"loss":0,"tie":0,"tooltip":null},"112.l.1889.t.6":{"win":2,"loss":8,"tie":0,"tooltip":"W: REB, AST\nL: FGM, FG%, FT%, 3PTM, PTS, ST, BLK, TO\nT: "},"112.l.1889.t.7":{"win":3,"loss":7,"tie":0,"tooltip":"W: REB, AST, ST\nL: FGM, FG%, FT%, 3PTM, PTS, BLK, TO\nT: "},"112.l.1889.t.8":{"win":9,"loss":1,"tie":0,"tooltip":"W: FGM, FG%, FT%, 3PTM, PTS, REB, AST, ST, BLK\nL: TO\nT: "},"total":{"win":32,"loss":37,"tie":1,"tooltip":"FGM: 3-4-0\nFG%: 1-6-0\nFT%: 1-6-0\n3PTM: 2-5-0\nPTS: 3-4-0\nREB: 7-0-0\nAST: 7-0-0\nST: 6-1-0\nBLK: 2-4-1\nTO: 0-7-0"}}},{"teamKey":"112.l.1889.t.6","cells":{"112.l.1889.t.1":{"win":7,"loss":3,"tie":0,"tooltip":"W: FGM, 3PTM, PTS, REB, AST, ST, BLK\nL: FG%, FT%, TO\nT: "},"112.l.1889.t.2":{"win":8,"loss":1,"tie":1,"tooltip":"W: FGM, FG%, FT%, 3PTM, PTS, REB, ST, BLK\nL: TO\nT: AST"},"112.l.1889.t.3":{"win":8,"loss":2,"tie":0,"tooltip":"W: FGM, FT%, 3PTM, PTS, REB, AST, ST, BLK\nL: FG%, TO\nT: "},"112.l.1889.t.4":{"win":7,"loss":3,"tie":0,"tooltip":"W: FGM, FT%, 3PTM, PTS, REB, ST, TO\nL: FG%, AST, BLK\nT: "},"112.l.1889.t.5":{"win":8,"loss":2,"tie":0,"tooltip":"W: FGM, FG%, FT%, 3PTM, PTS, ST, BLK, TO\nL: REB, AST\nT: "},"112.l.1889.t.6":{"win":0,"loss":0,"tie":0,"tooltip":null},"112.l.1889.t.7":{"win":7,"loss":3,"tie":0,"tooltip":"W: FGM, FT%, 3PTM, PTS, REB, ST, TO\nL: FG%, AST, BLK\nT: "},"112.l.1889.t.8":{"win":9,"loss":1,"tie":0,"tooltip":"W: FGM, FG%, FT%, 3PTM, PTS, REB, AST, ST, BLK\nL: TO\nT: "},"total":{"win":54,"loss":15,"tie":1,"tooltip":"FGM: 7-0-0\nFG%: 3-4-0\nFT%: 6-1-0\n3PTM: 7-0-0\nPTS: 7-0-0\nREB: 6-1-0\nAST: 3-3-1\nST: 7-0-0\nBLK: 5-2-0\nTO: 3-4-0"}}},{"teamKey":"112.l.1889.t.7","cells":{"112.l.1889.t.1":{"win":7,"loss":2,"tie":1,"tooltip":"W: FGM, FG%, PTS, REB, AST, ST, BLK\nL: FT%, TO\nT: 3PTM"},"112.l.1889.t.2":{"win":5,"loss":5,"tie":0,"tooltip":"W: FGM, FG%, AST, ST, BLK\nL: FT%, 3PTM, PTS, REB, TO\nT: "},"112.l.1889.t.3":{"win":9,"loss":1,"tie":0,"tooltip":"W: FGM, FG%, FT%, 3PTM, PTS, REB, AST, ST, BLK\nL: TO\nT: "},"112.l.1889.t.4":{"win":6,"loss":4,"tie":0,"tooltip":"W: FG%, 3PTM, PTS, REB, AST, ST\nL: FGM, FT%, BLK, TO\nT: "},"112.l.1889.t.5":{"win":7,"loss":3,"tie":0,"tooltip":"W: FGM, FG%, FT%, 3PTM, PTS, BLK, TO\nL: REB, AST, ST\nT: "},"112.l.1889.t.6":{"win":3,"loss":7,"tie":0,"tooltip":"W: FG%, AST, BLK\nL: FGM, FT%, 3PTM, PTS, REB, ST, TO\nT: "},"112.l.1889.t.7":{"win":0,"loss":0,"tie":0,"tooltip":null},"112.l.1889.t.8":{"win":9,"loss":1,"tie":0,"tooltip":"W: FGM, FG%, FT%, 3PTM, PTS, REB, AST, ST, BLK\nL: TO\nT: "},"total":{"win":46,"loss":23,"tie":1,"tooltip":"FGM: 5-2-0\nFG%: 7-0-0\nFT%: 3-4-0\n3PTM: 4-2-1\nPTS: 5-2-0\nREB: 4-3-0\nAST: 6-1-0\nST: 5-2-0\nBLK: 6-1-0\nTO: 1-6-0"}}},{"teamKey":"112.l.1889.t.8","cells":{"112.l.1889.t.1":{"win":1,"loss":9,"tie":0,"tooltip":"W: TO\nL: FGM, FG%, FT%, 3PTM, PTS, REB, AST, ST, BLK\nT: "},"112.l.1889.t.2":{"win":1,"loss":9,"tie":0,"tooltip":"W: TO\nL: FGM, FG%, FT%, 3PTM, PTS, REB, AST, ST, BLK\nT: "},"112.l.1889.t.3":{"win":1,"loss":9,"tie":0,"tooltip":"W: TO\nL: FGM, FG%, FT%, 3PTM, PTS, REB, AST, ST, BLK\nT: "},"112.l.1889.t.4":{"win":1,"loss":9,"tie":0,"tooltip":"W: TO\nL: FGM, FG%, FT%, 3PTM, PTS, REB, AST, ST, BLK\nT: "},"112.l.1889.t.5":{"win":1,"loss":9,"tie":0,"tooltip":"W: TO\nL: FGM, FG%, FT%, 3PTM, PTS, REB, AST, ST, BLK\nT: "},"112.l.1889.t.6":{"win":1,"loss":9,"tie":0,"tooltip":"W: TO\nL: FGM, FG%, FT%, 3PTM, PTS, REB, AST, ST, BLK\nT: "},"112.l.1889.t.7":{"win":1,"loss":9,"tie":0,"tooltip":"W: TO\nL: FGM, FG%, FT%, 3PTM, PTS, REB, AST, ST, BLK\nT: "},"112.l.1889.t.8":{"win":0,"loss":0,"tie":0,"tooltip":null},"total":{"win":7,"loss":63,"tie":0,"tooltip":"FGM: 0-7-0\nFG%: 0-7-0\nFT%: 0-7-0\n3PTM: 0-7-0\nPTS: 0-7-0\nREB: 0-7-0\nAST: 0-7-0\nST: 0-7-0\nBLK: 0-7-0\nTO: 7-0-0"}}}]}},"perGame":{"teamStats":{"headers":[],"rows":[["112.l.1889.t.1",32.0,32.0,23.0,33.875,5.78125,12.78125,0.45232273838630804,4.5625,5.5625,0.8202247191011236,1.0625,2.4375,0.4358974358974359,17.1875,1.34375,4.21875,5.5625,2.75,1.1875,0.78125,2.375],["112.l.1889.t.2",35.0,33.0,33.0,35.84848484848485,6.636363636363637,15.121212121212121,0.4388777555110221,5.424242424242424,7.0,0.7748917748917749,1.0909090909090908,2.9393939393939394,0.37113402061855666,19.78787878787879,1.606060606060606,5.96969696969697,7.575757575757576,3.212121212121212,1.0,0.5757575757575758,2.212121212121212],["112.l.1889.t.3",35.0,31.0,29.0,30.419354838709676,4.935483870967742,11.129032258064516,0.4434782608695652,3.3548387096774195,4.935483870967742,0.6797385620915033,0.4838709677419355,1.5483870967741935,0.3125,13.709677419354838,1.903225806451613,5.064516129032258,6.967741935483871,2.161290322580645,0.7096774193548387,1.0,1.935483870967742],["112.l.1889.t.4",38.0,31.0,30.0,36.645161290322584,7.225806451612903,15.193548387096774,0.47558386411889597,3.967741935483871,5.096774193548387,0.7784810126582279,0.7419354838709677,2.0,0.3709677419354839,19.161290322580644,2.0,4.870967741935484,6.870967741935484,4.064516129032258,1.1935483870967742,1.3870967741935485,2.5483870967741935],["112.l.1889.t.5",35.0,35.0,35.0,36.34285714285714,6.085714285714285,14.028571428571428,0.43380855397148677,4.142857142857143,6.142857142857143,0.6744186046511628,0.6285714285714286,2.1142857142857143,0.29729729729729726,16.942857142857143,2.0,5.542857142857143,7.542857142857143,4.742857142857143,1.3142857142857143,0.7142857142857143,3.3714285714285714],["112.l.1889.t.6",36.0,36.0,36.0,36.361111111111114,6.527777777777778,14.75,0.4425612052730697,4.416666666666667,5.527777777777778,0.7989949748743719,1.0833333333333333,2.9722222222222223,0.3644859813084112,18.555555555555557,1.6944444444444444,5.388888888888889,7.083333333333333,2.9444444444444446,1.3333333333333333,0.8888888888888888,2.1666666666666665],["112.l.1889.t.7",34.0,33.0,33.0,36.09090909090909,6.757575757575758,13.575757575757576,0.49776785714285715,4.363636363636363,6.242424242424242,0.6990291262135923,1.0303030303030303,2.1818181818181817,0.47222222222222227,18.90909090909091,1.5151515151515151,5.303030303030303,6.818181818181818,4.212121212121212,1.3636363636363635,1.0,2.787878787878788],["112.l.1889.t.8",0.0,null,null,null,null,null,null,null,null,null,null,null,null,null,null,null,null,null,null,null,null]]},"roto":{"headers":[],"rows":[["112.l.1889.t.4",8.0,7.0,6.0,4.0,7.0,4.0,6.0,5.0,8.0,4.0,59.0],["112.l.1889.t.7",7.0,8.0,4.0,5.0,6.0,3.0,7.0,8.0,6.5,3.0,57.5],["112.l.1889.t.6",5.0,4.0,7.0,7.0,5.0,6.0,4.0,7.0,5.0,7.0,57.0],["112.l.1889.t.2",6.0,3.0,5.0,8.0,8.0,8.0,5.0,3.0,2.0,6.0,54.0],["112.l.1889.t.1",3.0,6.0,8.0,6.0,4.0,2.0,3.0,4.0,4.0,5.0,45.0],["112.l.1889.t.5",4.0,2.0,2.0,3.0,3.0,7.0,8.0,6.0,3.0,2.0,40.0],["112.l.1889.t.3",2.0,5.0,3.0,2.0,2.0,5.0,2.0,2.0,6.5,8.0,37.5],["112.l.1889.t.8",1.0,1.0,1.0,1.0,1.0,1.0,1.0,1.0,1.0,1.0,10.0]]},"breakdown":{"rows":[{"teamKey":"112.l.1889.t.1","cells":{"112.l.1889.t.1":{"win":0,"loss":0,"tie":0,"tooltip":null},"112.l.1889.t.2":{"win":4,"loss":6,"tie":0,"tooltip":"W: FG%, FT%, ST, BLK\nL: FGM, 3PTM, PTS, REB, AST, TO\nT: "},"112.l.1889.t.3":{"win":7,"loss":3,"tie":0,"tooltip":"W: FGM, FG%, FT%, 3PTM, PTS, AST, ST\nL: REB, BLK, TO\nT: "},"112.l.1889.t.4":{"win":3,"loss":7,"tie":0,"tooltip":"W: FT%, 3PTM, TO\nL: FGM, FG%, PTS, REB, AST, ST, BLK\nT: "},"112.l.1889.t.5":{"win":6,"loss":4,"tie":0,"tooltip":"W: FG%, FT%, 3PTM, PTS, BLK, TO\nL: FGM, REB, AST, ST\nT: "},"112.l.1889.t.6":{"win":2,"loss":8,"tie":0,"tooltip":"W: FG%, FT%\nL: FGM, 3PTM, PTS, REB, AST, ST, BLK, TO\nT: "},"112.l.1889.t.7":{"win":3,"loss":7,"tie":0,"tooltip":"W: FT%, 3PTM, TO\nL: FGM, FG%, PTS, REB, AST, ST, BLK\nT: "},"112.l.1889.t.8":{"win":10,"loss":0,"tie":0,"tooltip":"W: FGM, FG%, FT%, 3PTM, PTS, REB, AST, ST, BLK, TO\nL: \nT: "},"total":{"win":35,"loss":35,"tie":0,"tooltip":"FGM: 2-5-0\nFG%: 5-2-0\nFT%: 7-0-0\n3PTM: 5-2-0\nPTS: 3-4-0\nREB: 1-6-0\nAST: 2-5-0\nST: 3-4-0\nBLK: 3-4-0\nTO: 4-3-0"}}},{"teamKey":"112.l.1889.t.2","cells":{"112.l.1889.t.1":{"win":6,"loss":4,"tie":0,"tooltip":"W: FGM, 3PTM, PTS, REB, AST, TO\nL: FG%, FT%, ST, BLK\nT: "},"112.l.1889.t.2":{"win":0,"loss":0,"tie":0,"tooltip":null},"112.l.1889.t.3":{"win":7,"loss":3,"tie":0,"tooltip":"W: FGM, FT%, 3PTM, PTS, REB, AST, ST\nL: FG%, BLK, TO\nT: "},"112.l.1889.t.4":{"win":4,"loss":6,"tie":0,"tooltip":"W: 3PTM, PTS, REB, TO\nL: FGM, FG%, FT%, AST, ST, BLK\nT: "},"112.l.1889.t.5":{"win":7,"loss":3,"tie":0,"tooltip":"W: FGM, FG%, FT%, 3PTM, PTS, REB, TO\nL: AST, ST, BLK\nT: "},"112.l.1889.t.6":{"win":5,"loss":5,"tie":0,"tooltip":"W: FGM, 3PTM, PTS, REB, AST\nL: FG%, FT%, ST, BLK, TO\nT: "},"112.l.1889.t.7":{"win":5,"loss":5,"tie":0,"tooltip":"W: FT%, 3PTM, PTS, REB, TO\nL: FGM, FG%, AST, ST, BLK\nT: "},"112.l.1889.t.8":{"win":10,"loss":0,"tie":0,"tooltip":"W: FGM, FG%, FT%, 3PTM, PTS, REB, AST, ST, BLK, TO\nL: \nT: "},"total":{"win":44,"loss":26,"tie":0,"tooltip":"FGM: 5-2-0\nFG%: 2-5-0\nFT%: 4-3-0\n3PTM: 7-0-0\nPTS: 7-0-0\nREB: 7-0-0\nAST: 4-3-0\nST: 2-5-0\nBLK: 1-6-0\nTO: 5-2-0"}}},{"teamKey":"112.l.1889.t.3","cells":{"112.l.1889.t.1":{"win":3,"loss":7,"tie":0,"tooltip":"W: REB, BLK, TO\nL: FGM, FG%, FT%, 3PTM, PTS, AST, ST\nT: "},"112.l.1889.t.2":{"win":3,"loss":7,"tie":0,"tooltip":"W: FG%, BLK, TO\nL: FGM, FT%, 3PTM, PTS, REB, AST, ST\nT: "},"112.l.1889.t.3":{"win":0,"loss":0,"tie":0,"tooltip":null},"112.l.1889.t.4":{"win":2,"loss":8,"tie":0,"tooltip":"W: REB, TO\nL: FGM, FG%, FT%, 3PTM, PTS, AST, ST, BLK\nT: "},"112.l.1889.t.5":{"win":4,"loss":6,"tie":0,"tooltip":"W: FG%, FT%, BLK, TO\nL: FGM, 3PTM, PTS, REB, AST, ST\nT: "},"112.l.1889.t.6":{"win":3,"loss":7,"tie":0,"tooltip":"W: FG%, BLK, TO\nL: FGM, FT%, 3PTM, PTS, REB, AST, ST\nT: "},"112.l.1889.t.7":{"win":2,"loss":7,"tie":1,"tooltip":"W: REB, TO\nL: FGM, FG%, FT%, 3PTM, PTS, AST, ST\nT: BLK"},"112.l.1889.t.8":{"win":10,"loss":0,"tie":0,"tooltip":"W: FGM, FG%, FT%, 3PTM, PTS, REB, AST, ST, BLK, TO\nL: \nT: "},"total":{"win":27,"loss":42,"tie":1,"tooltip":"FGM: 1-6-0\nFG%: 4-3-0\nFT%: 2-5-0\n3PTM: 1-6-0\nPTS: 1-6-0\nREB: 4-3-0\nAST: 1-6-0\nST: 1-6-0\nBLK: 5-1-1\nTO: 7-0-0"}}},{"teamKey":"112.l.1889.t.4","cells":{"112.l.1889.t.1":{"win":7,"loss":3,"tie":0,"tooltip":"W: FGM, FG%, PTS, REB, AST, ST, BLK\nL: FT%, 3PTM, TO\nT: "},"112.l.1889.t.2":{"win":6,"loss":4,"tie":0,"tooltip":"W: FGM, FG%, FT%, AST, ST, BLK\nL: 3PTM, PTS, REB, TO\nT: "},"112.l.1889.t.3":{"win":8,"loss":2,"tie":0,"tooltip":"W: FGM, FG%, FT%, 3PTM, PTS, AST, ST, BLK\nL: REB, TO\nT: "},"112.l.1889.t.4":{"win":0,"loss":0,"tie":0,"tooltip":null},"112.l.1889.t.5":{"win":7,"loss":3,"tie":0,"tooltip":"W: FGM, FG%, FT%, 3PTM, PTS, BLK, TO\nL: REB, AST, ST\nT: "},"112.l.1889.t.6":{"win":5,"loss":5,"tie":0,"tooltip":"W: FGM, FG%, PTS, AST, BLK\nL: FT%, 3PTM, REB, ST, TO\nT: "},"112.l.1889.t.7":{"win":6,"loss":4,"tie":0,"tooltip":"W: FGM, FT%, PTS, REB, BLK, TO\nL: FG%, 3PTM, AST, ST\nT: "},"112.l.1889.t.8":{"win":10,"loss":0,"tie":0,"tooltip":"W: FGM, FG%, FT%, 3PTM, PTS, REB, AST, ST, BLK, TO\nL: \nT: "},"total":{"win":49,"loss":21,"tie":0,"tooltip":"FGM: 7-0-0\nFG%: 6-1-0\nFT%: 5-2-0\n3PTM: 3-4-0\nPTS: 6-1-0\nREB: 3-4-0\nAST: 5-2-0\nST: 4-3-0\nBLK: 7-0-0\nTO: 3-4-0"}}},{"teamKey":"112.l.1889.t.5","cells":{"112.l.1889.t.1":{"win":4,"loss":6,"tie":0,"tooltip":"W: FGM, REB, AST, ST\nL: FG%, FT%, 3PTM, PTS, BLK, TO\nT: "},"112.l.1889.t.2":{"win":3,"loss":7,"tie":0,"tooltip":"W: AST, ST, BLK\nL: FGM, FG%, FT%, 3PTM, PTS, REB, TO\nT: "},"112.l.1889.t.3":{"win":6,"loss":4,"tie":0,"tooltip":"W: FGM, 3PTM, PTS, REB, AST, ST\nL: FG%, FT%, BLK, TO\nT: "},"112.l.1889.t.4":{"win":3,"loss":7,"tie":0,"tooltip":"W: REB, AST, ST\nL: FGM, FG%, FT%, 3PTM, PTS, BLK, TO\nT: "},"112.l.1889.t.5":{"win":0,"loss":0,"tie":0,"tooltip":null},"112.l.1889.t.6":{"win":2,"loss":8,"tie":0,"tooltip":"W: REB, AST\nL: FGM, FG%, FT%, 3PTM, PTS, ST, BLK, TO\nT: "},"112.l.1889.t.7":{"win":2,"loss":8,"tie":0,"tooltip":"W: REB, AST\nL: FGM, FG%, FT%, 3PTM, PTS, ST, BLK, TO\nT: "},"112.l.1889.t.8":{"win":10,"loss":0,"tie":0,"tooltip":"W: FGM, FG%, FT%, 3PTM, PTS, REB, AST, ST, BLK, TO\nL: \nT: "},"total":{"win":30,"loss":40,"tie":0,"tooltip":"FGM: 3-4-0\nFG%: 1-6-0\nFT%: 1-6-0\n3PTM: 2-5-0\nPTS: 2-5-0\nREB: 6-1-0\nAST: 7-0-0\nST: 5-2-0\nBLK: 2-5-0\nTO: 1-6-0"}}},{"teamKey":"112.l.1889.t.6","cells":{"112.l.1889.t.1":{"win":8,"loss":2,"tie":0,"tooltip":"W: FGM, 3PTM, PTS, REB, AST, ST, BLK, TO\nL: FG%, FT%\nT: "},"112.l.1889.t.2":{"win":5,"loss":5,"tie":0,"tooltip":"W: FG%, FT%, ST, BLK, TO\nL: FGM, 3PTM, PTS, REB, AST\nT: "},"112.l.1889.t.3":{"win":7,"loss":3,"tie":0,"tooltip":"W: FGM, FT%, 3PTM, PTS, REB, AST, ST\nL: FG%, BLK, TO\nT: "},"112.l.1889.t.4":{"win":5,"loss":5,"tie":0,"tooltip":"W: FT%, 3PTM, REB, ST, TO\nL: FGM, FG%, PTS, AST, BLK\nT: "},"112.l.1889.t.5":{"win":8,"loss":2,"tie":0,"tooltip":"W: FGM, FG%, FT%, 3PTM, PTS, ST, BLK, TO\nL: REB, AST\nT: "},"112.l.1889.t.6":{"win":0,"loss":0,"tie":0,"tooltip":null},"112.l.1889.t.7":{"win":4,"loss":6,"tie":0,"tooltip":"W: FT%, 3PTM, REB, TO\nL: FGM, FG%, PTS, AST, ST, BLK\nT: "},"112.l.1889.t.8":{"win":10,"loss":0,"tie":0,"tooltip":"W: FGM, FG%, FT%, 3PTM, PTS, REB, AST, ST, BLK, TO\nL: \nT: "},"total":{"win":47,"loss":23,"tie":0,"tooltip":"FGM: 4-3-0\nFG%: 3-4-0\nFT%: 6-1-0\n3PTM: 6-1-0\nPTS: 4-3-0\nREB: 5-2-0\nAST: 3-4-0\nST: 6-1-0\nBLK: 4-3-0\nTO: 6-1-0"}}},{"teamKey":"112.l.1889.t.7","cells":{"112.l.1889.t.1":{"win":7,"loss":3,"tie":0,"tooltip":"W: FGM, FG%, PTS, REB, AST, ST, BLK\nL: FT%, 3PTM, TO\nT: "},"112.l.1889.t.2":{"win":5,"loss":5,"tie":0,"tooltip":"W: FGM, FG%, AST, ST, BLK\nL: FT%, 3PTM, PTS, REB, TO\nT: "},"112.l.1889.t.3":{"win":7,"loss":2,"tie":1,"tooltip":"W: FGM, FG%, FT%, 3PTM, PTS, AST, ST\nL: REB, TO\nT: BLK"},"112.l.1889.t.4":{"win":4,"loss":6,"tie":0,"tooltip":"W: FG%, 3PTM, AST, ST\nL: FGM, FT%, PTS, REB, BLK, TO\nT: "},"112.l.1889.t.5":{"win":8,"loss":2,"tie":0,"tooltip":"W: FGM, FG%, FT%, 3PTM, PTS, ST, BLK, TO\nL: REB, AST\nT: "},"112.l.1889.t.6":{"win":6,"loss":4,"tie":0,"tooltip":"W: FGM, FG%, PTS, AST, ST, BLK\nL: FT%, 3PTM, REB, TO\nT: "},"112.l.1889.t.7":{"win":0,"loss":0,"tie":0,"tooltip":null},"112.l.1889.t.8":{"win":10,"loss":0,"tie":0,"tooltip":"W: FGM, FG%, FT%, 3PTM, PTS, REB, AST, ST, BLK, TO\nL: \nT: "},"total":{"win":47,"loss":22,"tie":1,"tooltip":"FGM: 6-1-0\nFG%: 7-0-0\nFT%: 3-4-0\n3PTM: 4-3-0\nPTS: 5-2-0\nREB: 2-5-0\nAST: 6-1-0\nST: 7-0-0\nBLK: 5-1-1\nTO: 2-5-0"}}},{"teamKey":"112.l.1889.t.8","cells":{"112.l.1889.t.1":{"win":0,"loss":10,"tie":0,"tooltip":"W: \nL: FGM, FG%, FT%, 3PTM, PTS, REB, AST, ST, BLK, TO\nT: "},"112.l.1889.t.2":{"win":0,"loss":10,"tie":0,"tooltip":"W: \nL: FGM, FG%, FT%, 3PTM, PTS, REB, AST, ST, BLK, TO\nT: "},"112.l.1889.t.3":{"win":0,"loss":10,"tie":0,"tooltip":"W: \nL: FGM, FG%, FT%, 3PTM, PTS, REB, AST, ST, BLK, TO\nT: "},"112.l.1889.t.4":{"win":0,"loss":10,"tie":0,"tooltip":"W: \nL: FGM, FG%, FT%, 3PTM, PTS, REB, AST, ST, BLK, TO\nT: "},"112.l.1889.t.5":{"win":0,"loss":10,"tie":0,"tooltip":"W: \nL: FGM, FG%, FT%, 3PTM, PTS, REB, AST, ST, BLK, TO\nT: "},"112.l.1889.t.6":{"win":0,"loss":10,"tie":0,"tooltip":"W: \nL: FGM, FG%, FT%, 3PTM, PTS, REB, AST, ST, BLK, TO\nT: "},"112.l.1889.t.7":{"win":0,"loss":10,"tie":0,"tooltip":"W: \nL: FGM, FG%, FT%, 3PTM, PTS, REB, AST, ST, BLK, TO\nT: "},"112.l.1889.t.8":{"win":0,"loss":0,"tie":0,"tooltip":null},"total":{"win":0,"loss":70,"tie":0,"tooltip":"FGM: 0-7-0\nFG%: 0-7-0\nFT%: 0-7-0\n3PTM: 0-7-0\nPTS: 0-7-0\nREB: 0-7-0\nAST: 0-7-0\nST: 0-7-0\nBLK: 0-7-0\nTO: 0-7-0"}}}]}}}